editscore/__init__.py
editscore/utils.py
editscore/vie_prompts.py
editscore/mllm_tools/__init__.py
editscore/mllm_tools/internvl35_lmdeploy.py
editscore/mllm_tools/openai.py
editscore/mllm_tools/qwen25vl.py
editscore/mllm_tools/qwen25vl_vllm.py
editscore/mllm_tools/utils.py
editscore-0.1.8.dist-info/licenses/LICENSE
examples/OmniGen2-RL/evaluation/GEdit-Bench/calculate_statistics.py
examples/OmniGen2-RL/evaluation/GEdit-Bench/inference.py
examples/OmniGen2-RL/evaluation/GEdit-Bench/inference_flux_kontext_dev.py
examples/OmniGen2-RL/evaluation/GEdit-Bench/inference_qwen_image.py
examples/OmniGen2-RL/evaluation/GEdit-Bench/select_best.py
examples/OmniGen2-RL/evaluation/GEdit-Bench/test_gedit_score.py
examples/OmniGen2-RL/evaluation/GEdit-Bench/viescore/__init__.py
examples/OmniGen2-RL/evaluation/GEdit-Bench/viescore/our_prompts.py
examples/OmniGen2-RL/evaluation/GEdit-Bench/viescore/parse_prompt.py
examples/OmniGen2-RL/evaluation/GEdit-Bench/viescore/utils.py
examples/OmniGen2-RL/evaluation/GEdit-Bench/viescore/vie_prompts.py
examples/OmniGen2-RL/evaluation/GEdit-Bench/viescore/mllm_tools/__init__.py
examples/OmniGen2-RL/evaluation/GEdit-Bench/viescore/mllm_tools/gemini.py
examples/OmniGen2-RL/evaluation/GEdit-Bench/viescore/mllm_tools/idefics2_eval.py
examples/OmniGen2-RL/evaluation/GEdit-Bench/viescore/mllm_tools/mantis_idefics2_eval.py
examples/OmniGen2-RL/evaluation/GEdit-Bench/viescore/mllm_tools/minicpmv_eval.py
examples/OmniGen2-RL/evaluation/GEdit-Bench/viescore/mllm_tools/openai.py
examples/OmniGen2-RL/evaluation/GEdit-Bench/viescore/mllm_tools/qwen25_eval.py
examples/OmniGen2-RL/evaluation/GEdit-Bench/viescore/mllm_tools/qwen25vl_eval.py
examples/OmniGen2-RL/evaluation/GEdit-Bench/viescore/mllm_tools/qwen25vl_vllm.py
examples/OmniGen2-RL/evaluation/GEdit-Bench/viescore/mllm_tools/utils.py
examples/OmniGen2-RL/omnigen2/__init__.py
examples/OmniGen2-RL/omnigen2/models/__init__.py
examples/OmniGen2-RL/omnigen2/models/attention_processor.py
examples/OmniGen2-RL/omnigen2/models/embeddings.py
editscore-0.1.8.dist-info/METADATA
editscore-0.1.8.dist-info/WHEEL
editscore-0.1.8.dist-info/top_level.txt
editscore-0.1.8.dist-info/RECORD
