Metadata-Version: 2.4
Name: editscore
Version: 0.1.8
Summary: A high-fidelity reward model for instruction-based image editing.
Author-email: Xin Luo <xinluo@mail.ustc.edu.cn>, Jiahao Wang <jiahaowang0917@gmail.com>, Chenyuan Wu <wuchenyuan@mail.ustc.edu.cn>
Project-URL: Homepage, https://github.com/VectorSpaceLab/EditScore
Project-URL: Issues, https://github.com/VectorSpaceLab/EditScore/issues
Classifier: Programming Language :: Python :: 3
Classifier: License :: OSI Approved :: Apache Software License
Classifier: Operating System :: OS Independent
Requires-Python: >=3.8
License-File: LICENSE
Requires-Dist: torch
Requires-Dist: torchvision
Requires-Dist: accelerate
Requires-Dist: transformers
Requires-Dist: qwen-vl-utils
Requires-Dist: peft
Requires-Dist: Pillow
Dynamic: license-file
